README.md
setup.py
isgitlabdown/__init__.py
isgitlabdown/__main__.py
isgitlabdown/isgitlabdown.py
isgitlabdown.egg-info/PKG-INFO
isgitlabdown.egg-info/SOURCES.txt
isgitlabdown.egg-info/dependency_links.txt
isgitlabdown.egg-info/entry_points.txt
isgitlabdown.egg-info/requires.txt
isgitlabdown.egg-info/top_level.txt